openph_demand/__init__.py
openph_demand/cooling_demand/__init__.py
openph_demand/cooling_demand/calc_periods.py
openph_demand/cooling_demand/cooling_demand.py
openph_demand/cooling_demand/peak_month.py
openph_demand/cooling_demand/peak_month_climate_data.py
openph_demand/get_solvers.py
openph_demand/ground/__init__.py
openph_demand/ground/calc_periods.py
openph_demand/ground/heat_flow_iterative_solvers.py
openph_demand/ground/heat_flow_step_1_solvers.py
openph_demand/ground/results_period.py
openph_demand/heating_demand/__init__.py
openph_demand/heating_demand/calc_periods.py
openph_demand/heating_demand/heating_demand.py
openph_demand/solvers.py
openph_demand-0.1.1.dist-info/WHEEL
openph_demand-0.1.1.dist-info/entry_points.txt
openph_demand-0.1.1.dist-info/METADATA
openph_demand-0.1.1.dist-info/RECORD
